LICENSE
MANIFEST.in
README.rst
setup.cfg
setup.py
comparator/__init__.py
comparator/data/ground_truth.csv
names_comparator.egg-info/PKG-INFO
names_comparator.egg-info/SOURCES.txt
names_comparator.egg-info/dependency_links.txt
names_comparator.egg-info/requires.txt
names_comparator.egg-info/top_level.txt