Metadata-Version: 1.1
Name: names-comparator
Version: 1.0.0
Summary: Simple tool to compare almost similar names which are coming from the same source (for example list of all company owners and officers of that company). Helps to cluster together persons with a slight difference in name spelling/typos. Better suited for Cyrillic names, but should work everywhere
Home-page: https://github.com/dchaplinsky/comparator
Author: dchaplinsky
Author-email: chaplinsky.dmitry@gmail.com
License: MIT
Keywords: names fuzzy comparison levenshtein
Platform: UNKNOWN
Classifier: Development Status :: 4 - Beta
Classifier: Intended Audience :: Developers
Classifier: License :: OSI Approved :: MIT License
Classifier: Programming Language :: Python :: 3
Classifier: Programming Language :: Python :: Implementation :: PyPy
Classifier: Programming Language :: Python :: 3.3
Classifier: Programming Language :: Python :: 3.4
Classifier: Programming Language :: Python :: 3.5
Classifier: Programming Language :: Python :: 3.6
Classifier: Natural Language :: Ukrainian
Classifier: Natural Language :: Russian
Classifier: Natural Language :: English
Classifier: Topic :: Text Processing :: Linguistic
Classifier: Topic :: Text Processing :: General
Classifier: Topic :: Text Processing :: Indexing
